[
  {
    "source": "wonju_health_medical_institution",
    "source_id": "13192935",
    "number_raw": "451",
    "category_raw": "한의원",
    "name_raw": "모아한의원",
    "address_raw": "강원특별자치도 원주시 원일로 63 (원동)",
    "phone_raw": "033-765-7533",
    "detail_url": "https://www.wonju.go.kr/health/viewTnResrceDataPA.do?resrceNo=13192935&sc1=10&si1=27&cpn=46&key=1787&from=",
    "map_action_raw": "href=#n | onclick=javascript:fn_setAddressToMapPosition('강원특별자치도 원주시 원일로 63 (원동)','모아한의원');",
    "page": 46,
    "row_index": 1,
    "source_url": "https://www.wonju.go.kr/health/selectResrceListPA3.do?key=1787&sc1=10&si1=27&cpn=46",
    "http_method": "GET",
    "collected_at": "2026-07-15T22:55:11+09:00"
  },
  {
    "source": "wonju_health_medical_institution",
    "source_id": "13192936",
    "number_raw": "452",
    "category_raw": "한의원",
    "name_raw": "경희 해맑은한의원",
    "address_raw": "강원특별자치도 원주시 시청로 98, 2층 (무실동)",
    "phone_raw": "033-744-1075",
    "detail_url": "https://www.wonju.go.kr/health/viewTnResrceDataPA.do?resrceNo=13192936&sc1=10&si1=27&cpn=46&key=1787&from=",
    "map_action_raw": "href=#n | onclick=javascript:fn_setAddressToMapPosition('강원특별자치도 원주시 시청로 98, 2층 (무실동)','경희 해맑은한의원');",
    "page": 46,
    "row_index": 2,
    "source_url": "https://www.wonju.go.kr/health/selectResrceListPA3.do?key=1787&sc1=10&si1=27&cpn=46",
    "http_method": "GET",
    "collected_at": "2026-07-15T22:55:11+09:00"
  },
  {
    "source": "wonju_health_medical_institution",
    "source_id": "13192937",
    "number_raw": "453",
    "category_raw": "한의원",
    "name_raw": "흥업한의원",
    "address_raw": "강원특별자치도 원주시 흥업면 남원로 67",
    "phone_raw": "033-762-6527",
    "detail_url": "https://www.wonju.go.kr/health/viewTnResrceDataPA.do?resrceNo=13192937&sc1=10&si1=27&cpn=46&key=1787&from=",
    "map_action_raw": "href=#n | onclick=javascript:fn_setAddressToMapPosition('강원특별자치도 원주시 흥업면 남원로 67','흥업한의원');",
    "page": 46,
    "row_index": 3,
    "source_url": "https://www.wonju.go.kr/health/selectResrceListPA3.do?key=1787&sc1=10&si1=27&cpn=46",
    "http_method": "GET",
    "collected_at": "2026-07-15T22:55:11+09:00"
  },
  {
    "source": "wonju_health_medical_institution",
    "source_id": "13192938",
    "number_raw": "454",
    "category_raw": "한의원",
    "name_raw": "인덕한의원",
    "address_raw": "강원특별자치도 원주시 남원로 589, 1층 (명륜동)",
    "phone_raw": "033-766-9966",
    "detail_url": "https://www.wonju.go.kr/health/viewTnResrceDataPA.do?resrceNo=13192938&sc1=10&si1=27&cpn=46&key=1787&from=",
    "map_action_raw": "href=#n | onclick=javascript:fn_setAddressToMapPosition('강원특별자치도 원주시 남원로 589, 1층 (명륜동)','인덕한의원');",
    "page": 46,
    "row_index": 4,
    "source_url": "https://www.wonju.go.kr/health/selectResrceListPA3.do?key=1787&sc1=10&si1=27&cpn=46",
    "http_method": "GET",
    "collected_at": "2026-07-15T22:55:11+09:00"
  },
  {
    "source": "wonju_health_medical_institution",
    "source_id": "13192939",
    "number_raw": "455",
    "category_raw": "한의원",
    "name_raw": "강남한의원",
    "address_raw": "강원특별자치도 원주시 남원로 441-2, 1층 (명륜동)",
    "phone_raw": "033-762-1275",
    "detail_url": "https://www.wonju.go.kr/health/viewTnResrceDataPA.do?resrceNo=13192939&sc1=10&si1=27&cpn=46&key=1787&from=",
    "map_action_raw": "href=#n | onclick=javascript:fn_setAddressToMapPosition('강원특별자치도 원주시 남원로 441-2, 1층 (명륜동)','강남한의원');",
    "page": 46,
    "row_index": 5,
    "source_url": "https://www.wonju.go.kr/health/selectResrceListPA3.do?key=1787&sc1=10&si1=27&cpn=46",
    "http_method": "GET",
    "collected_at": "2026-07-15T22:55:11+09:00"
  },
  {
    "source": "wonju_health_medical_institution",
    "source_id": "13192940",
    "number_raw": "456",
    "category_raw": "한의원",
    "name_raw": "권한의원",
    "address_raw": "강원특별자치도 원주시 치악로 1521, 2층 (관설동, 고려빌딩)",
    "phone_raw": "033-765-7657",
    "detail_url": "https://www.wonju.go.kr/health/viewTnResrceDataPA.do?resrceNo=13192940&sc1=10&si1=27&cpn=46&key=1787&from=",
    "map_action_raw": "href=#n | onclick=javascript:fn_setAddressToMapPosition('강원특별자치도 원주시 치악로 1521, 2층 (관설동, 고려빌딩)','권한의원');",
    "page": 46,
    "row_index": 6,
    "source_url": "https://www.wonju.go.kr/health/selectResrceListPA3.do?key=1787&sc1=10&si1=27&cpn=46",
    "http_method": "GET",
    "collected_at": "2026-07-15T22:55:11+09:00"
  },
  {
    "source": "wonju_health_medical_institution",
    "source_id": "13192941",
    "number_raw": "457",
    "category_raw": "한의원",
    "name_raw": "양상묵한의원",
    "address_raw": "강원특별자치도 원주시 남원로 528-13 (단구동)",
    "phone_raw": "033-766-3999",
    "detail_url": "https://www.wonju.go.kr/health/viewTnResrceDataPA.do?resrceNo=13192941&sc1=10&si1=27&cpn=46&key=1787&from=",
    "map_action_raw": "href=#n | onclick=javascript:fn_setAddressToMapPosition('강원특별자치도 원주시 남원로 528-13 (단구동)','양상묵한의원');",
    "page": 46,
    "row_index": 7,
    "source_url": "https://www.wonju.go.kr/health/selectResrceListPA3.do?key=1787&sc1=10&si1=27&cpn=46",
    "http_method": "GET",
    "collected_at": "2026-07-15T22:55:11+09:00"
  },
  {
    "source": "wonju_health_medical_institution",
    "source_id": "13192942",
    "number_raw": "458",
    "category_raw": "한의원",
    "name_raw": "지선당한의원",
    "address_raw": "강원특별자치도 원주시 능라동길 51, 517, 518호 (무실동)",
    "phone_raw": "033-748-1075",
    "detail_url": "https://www.wonju.go.kr/health/viewTnResrceDataPA.do?resrceNo=13192942&sc1=10&si1=27&cpn=46&key=1787&from=",
    "map_action_raw": "href=#n | onclick=javascript:fn_setAddressToMapPosition('강원특별자치도 원주시 능라동길 51, 517, 518호 (무실동)','지선당한의원');",
    "page": 46,
    "row_index": 8,
    "source_url": "https://www.wonju.go.kr/health/selectResrceListPA3.do?key=1787&sc1=10&si1=27&cpn=46",
    "http_method": "GET",
    "collected_at": "2026-07-15T22:55:11+09:00"
  },
  {
    "source": "wonju_health_medical_institution",
    "source_id": "13192943",
    "number_raw": "459",
    "category_raw": "한의원",
    "name_raw": "예인한의원",
    "address_raw": "강원특별자치도 원주시 단관길 129 (관설동)",
    "phone_raw": "033-763-3555",
    "detail_url": "https://www.wonju.go.kr/health/viewTnResrceDataPA.do?resrceNo=13192943&sc1=10&si1=27&cpn=46&key=1787&from=",
    "map_action_raw": "href=#n | onclick=javascript:fn_setAddressToMapPosition('강원특별자치도 원주시 단관길 129 (관설동)','예인한의원');",
    "page": 46,
    "row_index": 9,
    "source_url": "https://www.wonju.go.kr/health/selectResrceListPA3.do?key=1787&sc1=10&si1=27&cpn=46",
    "http_method": "GET",
    "collected_at": "2026-07-15T22:55:11+09:00"
  },
  {
    "source": "wonju_health_medical_institution",
    "source_id": "13192944",
    "number_raw": "460",
    "category_raw": "한의원",
    "name_raw": "평강한의원",
    "address_raw": "강원특별자치도 원주시 원일로115번길 5, 2층 (일산동)",
    "phone_raw": "033-732-5551",
    "detail_url": "https://www.wonju.go.kr/health/viewTnResrceDataPA.do?resrceNo=13192944&sc1=10&si1=27&cpn=46&key=1787&from=",
    "map_action_raw": "href=#n | onclick=javascript:fn_setAddressToMapPosition('강원특별자치도 원주시 원일로115번길 5, 2층 (일산동)','평강한의원');",
    "page": 46,
    "row_index": 10,
    "source_url": "https://www.wonju.go.kr/health/selectResrceListPA3.do?key=1787&sc1=10&si1=27&cpn=46",
    "http_method": "GET",
    "collected_at": "2026-07-15T22:55:11+09:00"
  }
]